usdol_wage_determination_model/__init__.py
usdol_wage_determination_model/construction_type.py
usdol_wage_determination_model/date_range.py
usdol_wage_determination_model/holiday.py
usdol_wage_determination_model/job.py
usdol_wage_determination_model/location.py
usdol_wage_determination_model/wage.py
usdol_wage_determination_model/wage_determination.py
usdol_wage_determination_model/zone.py
usdol_wage_determination_model-0.4.0.dist-info/METADATA
usdol_wage_determination_model-0.4.0.dist-info/WHEEL
usdol_wage_determination_model-0.4.0.dist-info/licenses/LICENSE.md
usdol_wage_determination_model-0.4.0.dist-info/RECORD
