Metadata-Version: 2.4
Name: usdol-wage-determination-model
Version: 0.4.0
Summary: Pydantic model for USDOL prevailing wage determination records
Author-email: Grey Flannel Consulting <contact@greyflannelconsulting.com>
License: Copyright (c) 2025 Grey Flannel Consulting, LLC.
License-File: LICENSE.md
Requires-Python: >=3.11
Requires-Dist: pycountry>=24.6.1
Requires-Dist: pydantic-extra-types>=2.10.5
Requires-Dist: pydantic>=2.11.7
